simple_computervision/__init__.py
simple_computervision/computervision.py
simple_computervision/logger.py
simple_computervision-0.0.2.dist-info/LICENSE
simple_computervision-0.0.2.dist-info/METADATA
simple_computervision-0.0.2.dist-info/WHEEL
simple_computervision-0.0.2.dist-info/top_level.txt
simple_computervision-0.0.2.dist-info/RECORD
